ceylon-0.23.0.dist-info/METADATA
ceylon-0.23.0.dist-info/WHEEL
ceylon-0.23.0.dist-info/licenses/LICENSE
ceylon/base/agents.py
ceylon/base/playground.py
ceylon/base/support.py
ceylon/base/uni_agent.py
ceylon/base/__init__.py
ceylon/llm/agent.py
ceylon/llm/data.py
ceylon/llm/models/ollama.py
ceylon/llm/models/support/http.py
ceylon/llm/models/support/messages.py
ceylon/llm/models/support/settings.py
ceylon/llm/models/support/tools.py
ceylon/llm/models/support/usage.py
ceylon/llm/models/support/__init__.py
ceylon/llm/models/__init__.py
ceylon/llm/__init__.py
ceylon/processor/agent.py
ceylon/processor/data.py
ceylon/processor/playground.py
ceylon/processor/__init__.py
ceylon/static_val.py
ceylon/task/data.py
ceylon/task/manager.py
ceylon/task/playground.py
ceylon/task/__init__.py
ceylon/__init__.py
ceylon/ceylon/__init__.py
ceylon/ceylon/ceylon.py
ceylon/ceylon/uniffi_ceylon.dll
ceylon-0.23.0.dist-info/RECORD
