Metadata-Version: 2.4
Name: ceylon
Version: 0.23.0
Classifier: Programming Language :: Rust
Classifier: Programming Language :: Python :: Implementation :: CPython
Classifier: Programming Language :: Python :: Implementation :: PyPy
Classifier: Operating System :: OS Independent
Classifier: License :: OSI Approved :: Apache Software License
Classifier: Topic :: Scientific/Engineering :: Artificial Intelligence
Classifier: Programming Language :: Python :: 3.7
Classifier: Programming Language :: Python :: 3.8
Classifier: Programming Language :: Python :: 3.9
Classifier: Programming Language :: Python :: 3.10
Classifier: Programming Language :: Python :: 3.11
Classifier: Programming Language :: Python :: 3.12
Requires-Dist: networkx==3.4.2
Requires-Dist: pydantic==2.10.6
Requires-Dist: toml==0.10.2
Requires-Dist: loguru==0.7.3
License-File: LICENSE
Summary: Ceylon is an advanced multi-agent platform specifically developed for Ceylon Aritficial Intelligence.
Keywords: Aritifical Intelligence,Multi Agent Systems,CEYLON,Ceylon Aritficial Intelligence.
Author: Syigen Ltd. <dewmal@syigen.com>
Author-email: Syigen Ltd. <dewmal@syigen.com>
License: Apache-2.0
Requires-Python: >=3.7
Project-URL: Homepage, https://ceylon.ai
Project-URL: Documentation, https://docs.ceylon.ai
Project-URL: Repository, https://github.com/ceylonai/ceylon
Project-URL: Issues, https://github.com/ceylonai/ceylon/issues
Project-URL: Changelog, https://github.com/ceylonai/ceylon/blob/master/CHANGELOG.md
